geomkit/__init__.py
geomkit/py.typed
geomkit/curves/__init__.py
geomkit/curves/bezier.py
geomkit/operations/__init__.py
geomkit/operations/utils.py
geomkit/primitives/__init__.py
geomkit/primitives/line.py
geomkit/primitives/matrix.py
geomkit/primitives/point.py
geomkit/primitives/vector.py
geomkit/shapes/__init__.py
geomkit/shapes/boundingbox.py
geomkit/shapes/circle.py
geomkit/shapes/polygon.py
geomkit/shapes/shapes3d.py
geomkit-0.2.0.dist-info/licenses/LICENSE
geomkit-0.2.0.dist-info/METADATA
geomkit-0.2.0.dist-info/WHEEL
geomkit-0.2.0.dist-info/top_level.txt
geomkit-0.2.0.dist-info/RECORD
