Metadata-Version: 2.4
Name: geomkit
Version: 0.2.0
Summary: A comprehensive Python library for 2D and 3D geometric operations
Home-page: https://github.com/mmssajith/geomkit
Author: Mohamed Sajith
Author-email: Mohamed Sajith <mmssajith@gmail.com>
Maintainer-email: Mohamed Sajith <mmssajith@gmail.com>
License: MIT
Project-URL: Homepage, https://github.com/mmssajith/geomkit
Project-URL: Documentation, https://github.com/mmssajith/geomkit#readme
Project-URL: Repository, https://github.com/mmssajith/geomkit
Project-URL: Bug Tracker, https://github.com/mmssajith/geomkit/issues
Project-URL: Changelog, https://github.com/mmssajith/geomkit/blob/main/CHANGELOG.md
Keywords: geometry,mathematics,computational-geometry,2d,3d,vector,point,line,circle,ellipse,polygon,triangle,shapes,geometric-algorithms,math-library
Classifier: Development Status :: 4 - Beta
Classifier: Intended Audience :: Developers
Classifier: Intended Audience :: Education
Classifier: Intended Audience :: Science/Research
Classifier: License :: OSI Approved :: MIT License
Classifier: Operating System :: OS Independent
Classifier: Programming Language :: Python :: 3
Classifier: Programming Language :: Python :: 3.8
Classifier: Programming Language :: Python :: 3.9
Classifier: Programming Language :: Python :: 3.10
Classifier: Programming Language :: Python :: 3.11
Classifier: Programming Language :: Python :: 3.12
Classifier: Programming Language :: Python :: 3.13
Classifier: Topic :: Scientific/Engineering :: Mathematics
Classifier: Topic :: Software Development :: Libraries :: Python Modules
Classifier: Typing :: Typed
Requires-Python: >=3.8
License-File: LICENSE
Provides-Extra: dev
Requires-Dist: pytest>=7.0.0; extra == "dev"
Requires-Dist: pytest-cov>=4.0.0; extra == "dev"
Requires-Dist: ruff>=0.1.0; extra == "dev"
Requires-Dist: mypy>=1.0.0; extra == "dev"
Provides-Extra: docs
Requires-Dist: sphinx>=5.0.0; extra == "docs"
Requires-Dist: sphinx-rtd-theme>=1.0.0; extra == "docs"
Dynamic: author
Dynamic: home-page
Dynamic: license-file
Dynamic: requires-python
